Metadata-Version: 2.1
Name: torchtemplates
Version: 1.0.0
Summary: A package to create pytorch projects quickly
Home-page: https://github.com/aneesh-aparajit/torchtemplates
Author: Aneesh Aparajit G
Author-email: aneeshaparajit.g2002@gmail.com
Classifier: Development Status :: 3 - Alpha
Classifier: Intended Audience :: Developers
Classifier: Programming Language :: Python :: 3
Requires-Dist: torch
Requires-Dist: albumentations
Requires-Dist: numpy
Requires-Dist: pandas
Requires-Dist: matplotlib
Requires-Dist: click
Requires-Dist: jinja2
Requires-Dist: wandb
Requires-Dist: transformers
Requires-Dist: rich
Requires-Dist: optuna
Requires-Dist: tqdm
